YOLOv7Detector/__init__.py
YOLOv7Detector/image_funcs.py
YOLOv7Detector/model.py
YOLOv7Detector/yolov7/__init__.py
YOLOv7Detector/yolov7/detect.py
YOLOv7Detector/yolov7/export.py
YOLOv7Detector/yolov7/hubconf.py
YOLOv7Detector/yolov7/test.py
YOLOv7Detector/yolov7/train.py
YOLOv7Detector/yolov7/train_aux.py
YOLOv7Detector/yolov7/deploy/__init__.py
YOLOv7Detector/yolov7/deploy/triton-inference-server/__init__.py
YOLOv7Detector/yolov7/deploy/triton-inference-server/boundingbox.py
YOLOv7Detector/yolov7/deploy/triton-inference-server/client.py
YOLOv7Detector/yolov7/deploy/triton-inference-server/labels.py
YOLOv7Detector/yolov7/deploy/triton-inference-server/processing.py
YOLOv7Detector/yolov7/deploy/triton-inference-server/render.py
YOLOv7Detector/yolov7/models/__init__.py
YOLOv7Detector/yolov7/models/common.py
YOLOv7Detector/yolov7/models/experimental.py
YOLOv7Detector/yolov7/models/yolo.py
YOLOv7Detector/yolov7/utils/__init__.py
YOLOv7Detector/yolov7/utils/activations.py
YOLOv7Detector/yolov7/utils/add_nms.py
YOLOv7Detector/yolov7/utils/autoanchor.py
YOLOv7Detector/yolov7/utils/datasets.py
YOLOv7Detector/yolov7/utils/general.py
YOLOv7Detector/yolov7/utils/google_utils.py
YOLOv7Detector/yolov7/utils/loss.py
YOLOv7Detector/yolov7/utils/metrics.py
YOLOv7Detector/yolov7/utils/plots.py
YOLOv7Detector/yolov7/utils/torch_utils.py
YOLOv7Detector/yolov7/utils/aws/__init__.py
YOLOv7Detector/yolov7/utils/aws/resume.py
YOLOv7Detector/yolov7/utils/wandb_logging/__init__.py
YOLOv7Detector/yolov7/utils/wandb_logging/log_dataset.py
YOLOv7Detector/yolov7/utils/wandb_logging/wandb_utils.py
YOLOv7Detector-0.0.5.dist-info/LICENSE.md
YOLOv7Detector-0.0.5.dist-info/METADATA
YOLOv7Detector-0.0.5.dist-info/WHEEL
YOLOv7Detector-0.0.5.dist-info/top_level.txt
YOLOv7Detector-0.0.5.dist-info/RECORD
