Metadata-Version: 2.1
Name: YOLOv7Detector
Version: 0.0.5
Summary: A simple Wrapper for YOLOv7
Home-page: https://github.com/SSaoulis/YOLOv7Detector
Author: Stefan Saoulis
Author-email: stefan.sooley@gmail.com
Requires-Python: >=3.6
License-File: LICENSE.md
Requires-Dist: matplotlib >=3.2.2
Requires-Dist: numpy <1.24.0,>=1.18.5
Requires-Dist: opencv-python >=4.1.1
Requires-Dist: Pillow >=7.1.2
Requires-Dist: PyYAML >=5.3.1
Requires-Dist: requests >=2.23.0
Requires-Dist: scipy >=1.4.1
Requires-Dist: torch !=1.12.0,>=1.7.0
Requires-Dist: torchvision !=0.13.0,>=0.8.1
Requires-Dist: tqdm >=4.41.0
Requires-Dist: protobuf
Requires-Dist: tensorboard >=2.4.1
Requires-Dist: pandas >=1.1.4
Requires-Dist: seaborn >=0.11.0
Requires-Dist: ipython
Requires-Dist: psutil
Requires-Dist: thop
